placekey/__init__.py
placekey/__version__.py
placekey/api.py
placekey/general.py
placekey/placekey.py
placekey-0.0.35.dist-info/LICENSE
placekey-0.0.35.dist-info/METADATA
placekey-0.0.35.dist-info/WHEEL
placekey-0.0.35.dist-info/top_level.txt
placekey-0.0.35.dist-info/RECORD
