Metadata-Version: 2.2
Name: placekey
Version: 0.0.35
Summary: Utilities for working with Placekeys
Home-page: https://github.com/Placekey/placekey-py
Author: SafeGraph Inc.
Author-email: russ@safegraph.com
Classifier: Programming Language :: Python :: 3
Classifier: License :: OSI Approved :: Apache Software License
Classifier: Operating System :: OS Independent
Requires-Python: >=3.8
License-File: LICENSE
Requires-Dist: h3<5,>=4.2.1
Requires-Dist: shapely
Requires-Dist: requests
Requires-Dist: ratelimit
Requires-Dist: backoff
Requires-Dist: boto3
Requires-Dist: pandas
Dynamic: author
Dynamic: author-email
Dynamic: classifier
Dynamic: description
Dynamic: description-content-type
Dynamic: home-page
Dynamic: requires-dist
Dynamic: requires-python
Dynamic: summary
